MANIFEST.in
README
README.rst
setup.py
cmsplugin_tumblr.egg-info/PKG-INFO
cmsplugin_tumblr.egg-info/SOURCES.txt
cmsplugin_tumblr.egg-info/dependency_links.txt
cmsplugin_tumblr.egg-info/not-zip-safe
cmsplugin_tumblr.egg-info/top_level.txt
tumblr_plugin/__init__.py
tumblr_plugin/cms_plugins.py
tumblr_plugin/models.py
tumblr_plugin/tumblr.py