Metadata-Version: 1.0
Name: cmsplugin-tumblr
Version: 1.0
Summary: A django-cms plugin that displays the last number of posts of a tumblr user
Home-page: https://github.com/sclaughl/cmsplugin-tumblr
Author: Stuart Laughlin
Author-email: stuart@bistrotech.net
License: UNKNOWN
Platform: UNKNOWN
